sekupy/__init__.py
sekupy/base.py
sekupy/mixin.py
sekupy/analysis/__init__.py
sekupy/analysis/base.py
sekupy/analysis/configurator.py
sekupy/analysis/glm.py
sekupy/analysis/iterator.py
sekupy/analysis/linear_model.py
sekupy/analysis/pipeline.py
sekupy/analysis/roi.py
sekupy/analysis/utils.py
sekupy/analysis/wrappers.py
sekupy/analysis/connectivity/__init__.py
sekupy/analysis/connectivity/base.py
sekupy/analysis/connectivity/meg.py
sekupy/analysis/connectivity/multivariate.py
sekupy/analysis/connectivity/topology.py
sekupy/analysis/decoding/__init__.py
sekupy/analysis/decoding/cross_decoding.py
sekupy/analysis/decoding/regression.py
sekupy/analysis/decoding/roi_decoding.py
sekupy/analysis/decoding/temporal_decoding.py
sekupy/analysis/fingerprint/__init__.py
sekupy/analysis/fingerprint/fingerprint.py
sekupy/analysis/fingerprint/task_prediction.py
sekupy/analysis/rsa/__init__.py
sekupy/analysis/rsa/rsa.py
sekupy/analysis/searchlight/__init__.py
sekupy/analysis/searchlight/temporal_searchlight.py
sekupy/analysis/states/__init__.py
sekupy/analysis/states/base.py
sekupy/analysis/states/gsbs.py
sekupy/analysis/states/metrics.py
sekupy/analysis/states/pipeline.py
sekupy/analysis/states/plot.py
sekupy/analysis/states/subsamplers.py
sekupy/dataset/__init__.py
sekupy/dataset/atoms.py
sekupy/dataset/base.py
sekupy/dataset/collections.py
sekupy/dataset/dataset.py
sekupy/dataset/detrend.py
sekupy/dataset/events.py
sekupy/dataset/learner.py
sekupy/dataset/mappers.py
sekupy/dataset/mri.py
sekupy/dataset/selector.py
sekupy/dataset/state.py
sekupy/dataset/utils.py
sekupy/dataset/zscore.py
sekupy/ext/__init__.py
sekupy/ext/nilearn/__init__.py
sekupy/ext/nilearn/searchlight.py
sekupy/ext/nilearn/utils.py
sekupy/ext/sklearn/__init__.py
sekupy/ext/sklearn/_split.py
sekupy/ext/sklearn/_validation.py
sekupy/ext/sklearn/cluster.py
sekupy/ext/sklearn/feature_selection.py
sekupy/glm/__init__.py
sekupy/io/__init__.py
sekupy/io/base.py
sekupy/io/bids.py
sekupy/io/configuration.py
sekupy-0.0.1.dist-info/METADATA
sekupy-0.0.1.dist-info/WHEEL
sekupy-0.0.1.dist-info/licenses/LICENSE
sekupy-0.0.1.dist-info/RECORD
