Metadata-Version: 2.3
Name: sekupy
Version: 0.0.1
Summary: Detergent for your dirty neuroimaging pipelines
Project-URL: Homepage, https://github.com/robbisg/sekupy
Project-URL: Bug Tracker, https://github.com/robbisg/sekupy/issues/
Project-URL: Documentation, https://sekupy.readthedocs.io/
Project-URL: Source Code, https://github.com/robbisg/sekupy
Author-email: Roberto Guidotti <roberto.guidotti@unich.it>
License: License for sekupy
License-File: LICENSE
Keywords: EEG,MEG,MVPA,brain,fMRI,machine learning,neuroimaging,neuroscience
Classifier: Intended Audience :: Developers
Classifier: Intended Audience :: Science/Research
Classifier: License :: OSI Approved
Classifier: Operating System :: MacOS
Classifier: Operating System :: Microsoft :: Windows
Classifier: Operating System :: POSIX
Classifier: Operating System :: Unix
Classifier: Programming Language :: Python
Classifier: Programming Language :: Python :: 3
Classifier: Topic :: Scientific/Engineering
Classifier: Topic :: Software Development
Requires-Python: >=3.9
Requires-Dist: h5py
Requires-Dist: imbalanced-learn
Requires-Dist: lazy-loader
Requires-Dist: matplotlib
Requires-Dist: mne
Requires-Dist: nibabel
Requires-Dist: nilearn
Requires-Dist: numpy
Requires-Dist: pandas
Requires-Dist: pybids
Requires-Dist: pymatreader
Requires-Dist: scikit-learn
Requires-Dist: scipy
Requires-Dist: seaborn
Requires-Dist: statsmodels
Requires-Dist: tqdm
Provides-Extra: data
Provides-Extra: doc
Requires-Dist: graphviz; extra == 'doc'
Requires-Dist: ipython!=8.7.0; extra == 'doc'
Requires-Dist: memory-profiler; extra == 'doc'
Requires-Dist: mne-bids; extra == 'doc'
Requires-Dist: mne-connectivity; extra == 'doc'
Requires-Dist: mne-gui-addons; extra == 'doc'
Requires-Dist: neo; extra == 'doc'
Requires-Dist: numpydoc; extra == 'doc'
Requires-Dist: pydata-sphinx-theme==0.13.3; extra == 'doc'
Requires-Dist: pygments>=2.13; extra == 'doc'
Requires-Dist: pytest; extra == 'doc'
Requires-Dist: pyxdf; extra == 'doc'
Requires-Dist: pyzmq!=24.0.0; extra == 'doc'
Requires-Dist: seaborn!=0.11.2; extra == 'doc'
Requires-Dist: selenium; extra == 'doc'
Requires-Dist: sphinx-copybutton; extra == 'doc'
Requires-Dist: sphinx-design; extra == 'doc'
Requires-Dist: sphinx-gallery; extra == 'doc'
Requires-Dist: sphinx>=6; extra == 'doc'
Requires-Dist: sphinxcontrib-bibtex>=2.5; extra == 'doc'
Requires-Dist: sphinxcontrib-towncrier; extra == 'doc'
Requires-Dist: sphinxcontrib-youtube; extra == 'doc'
Provides-Extra: test
Requires-Dist: codespell; extra == 'test'
Requires-Dist: mypy; extra == 'test'
Requires-Dist: numpydoc; extra == 'test'
Requires-Dist: pre-commit; extra == 'test'
Requires-Dist: pytest-cov; extra == 'test'
Requires-Dist: pytest-harvest; extra == 'test'
Requires-Dist: pytest-qt; extra == 'test'
Requires-Dist: pytest-timeout; extra == 'test'
Requires-Dist: pytest>=8.0.0rc2; extra == 'test'
Requires-Dist: ruff; extra == 'test'
Requires-Dist: tomli; (python_version < '3.11') and extra == 'test'
Requires-Dist: twine; extra == 'test'
Requires-Dist: wheel; extra == 'test'
